gflanguages/__init__.py
gflanguages/_version.py
gflanguages/languages_public_pb2.py
gflanguages/data/languages/aa_Latn.textproto
gflanguages/data/languages/ab_Cyrl.textproto
gflanguages/data/languages/abi_Latn.textproto
gflanguages/data/languages/abq_Cyrl.textproto
gflanguages/data/languages/abr_Latn.textproto
gflanguages/data/languages/acd_Latn.textproto
gflanguages/data/languages/ace_Latn.textproto
gflanguages/data/languages/acf_Latn.textproto
gflanguages/data/languages/ach_Latn.textproto
gflanguages/data/languages/acu_Latn.textproto
gflanguages/data/languages/ada_Latn.textproto
gflanguages/data/languages/ade_Latn.textproto
gflanguages/data/languages/adj_Latn.textproto
gflanguages/data/languages/adl_Latn.textproto
gflanguages/data/languages/ady_Cyrl.textproto
gflanguages/data/languages/ae_Avst.textproto
gflanguages/data/languages/aeb_Arab.textproto
gflanguages/data/languages/aeb_Latn.textproto
gflanguages/data/languages/af_Latn.textproto
gflanguages/data/languages/agc_Latn.textproto
gflanguages/data/languages/agq_Latn.textproto
gflanguages/data/languages/agr_Latn.textproto
gflanguages/data/languages/aha_Latn.textproto
gflanguages/data/languages/ahl_Latn.textproto
gflanguages/data/languages/aho_Ahom.textproto
gflanguages/data/languages/ahs_Latn.textproto
gflanguages/data/languages/aii_Armi.textproto
gflanguages/data/languages/aii_Brah.textproto
gflanguages/data/languages/aii_Chrs.textproto
gflanguages/data/languages/aii_Cyrl.textproto
gflanguages/data/languages/aii_Egyp.textproto
gflanguages/data/languages/aii_Elym.textproto
gflanguages/data/languages/aii_Hatr.textproto
gflanguages/data/languages/aii_Latn.textproto
gflanguages/data/languages/aii_Mani.textproto
gflanguages/data/languages/aii_Narb.textproto
gflanguages/data/languages/aii_Nbat.textproto
gflanguages/data/languages/aii_Palm.textproto
gflanguages/data/languages/aii_Phli.textproto
gflanguages/data/languages/aii_Phlp.textproto
gflanguages/data/languages/aii_Phnx.textproto
gflanguages-5.0.4.dist-info/AUTHORS.txt
gflanguages-5.0.4.dist-info/LICENSE.txt
gflanguages-5.0.4.dist-info/METADATA
gflanguages-5.0.4.dist-info/WHEEL
gflanguages-5.0.4.dist-info/top_level.txt
gflanguages-5.0.4.dist-info/RECORD
