Metadata-Version: 2.1
Name: gflanguages
Version: 5.0.4
Summary: A python API for evaluating language support in the Google Fonts collection.
Home-page: https://github.com/googlefonts/lang/
Author: Dave Crossland, Felipe Sanches, Marc Foley, Roderick Sheeter
Author-email: dave@lab6.com
Classifier: Intended Audience :: Developers
Classifier: Topic :: Text Processing :: Fonts
Classifier: License :: OSI Approved :: Apache Software License
Classifier: Operating System :: OS Independent
Classifier: Programming Language :: Python :: 3
Requires-Python: >=3.7
License-File: LICENSE.txt
License-File: AUTHORS.txt
Requires-Dist: protobuf (<4,>=3.7.0)
